Metadata-Version: 1.0
Name: canonicalwebteam.yaml-deleted-paths
Version: 0.1.0
Summary: Show 410 pages for paths listed in a YAML file.
Home-page: https://github.com/ubuntudesign/yaml-deleted-paths
Author: Canonical Webteam
Author-email: UNKNOWN
License: UNKNOWN
Platform: UNKNOWN
